DuizhengXiayaoZhinvxingFenleixue/README.md
DuizhengXiayaoZhinvxingFenleixue/__init__.py
DuizhengXiayaoZhinvxingFenleixue/__main__.py
DuizhengXiayaoZhinvxingFenleixue/file.epub
DuizhengXiayaoZhinvxingFenleixue/index.html
DuizhengXiayaoZhinvxingFenleixue/css/__init__.py
DuizhengXiayaoZhinvxingFenleixue/css/annotations.css
DuizhengXiayaoZhinvxingFenleixue/css/main.css
DuizhengXiayaoZhinvxingFenleixue/css/normalize.css
DuizhengXiayaoZhinvxingFenleixue/css/popup.css
DuizhengXiayaoZhinvxingFenleixue/font/__init__.py
DuizhengXiayaoZhinvxingFenleixue/font/fontello.eot
DuizhengXiayaoZhinvxingFenleixue/font/fontello.svg
DuizhengXiayaoZhinvxingFenleixue/font/fontello.ttf
DuizhengXiayaoZhinvxingFenleixue/font/fontello.woff
DuizhengXiayaoZhinvxingFenleixue/img/__init__.py
DuizhengXiayaoZhinvxingFenleixue/img/annotator-glyph-sprite.png
DuizhengXiayaoZhinvxingFenleixue/img/annotator-icon-sprite.png
DuizhengXiayaoZhinvxingFenleixue/img/apple-touch-icon.png
DuizhengXiayaoZhinvxingFenleixue/img/cancelfullscreen.png
DuizhengXiayaoZhinvxingFenleixue/img/close.png
DuizhengXiayaoZhinvxingFenleixue/img/fullscreen.png
DuizhengXiayaoZhinvxingFenleixue/img/loader.gif
DuizhengXiayaoZhinvxingFenleixue/img/menu-icon.png
DuizhengXiayaoZhinvxingFenleixue/img/save.png
DuizhengXiayaoZhinvxingFenleixue/img/saved.png
DuizhengXiayaoZhinvxingFenleixue/img/settings-s.png
DuizhengXiayaoZhinvxingFenleixue/img/settings.png
DuizhengXiayaoZhinvxingFenleixue/img/star.png
DuizhengXiayaoZhinvxingFenleixue/js/__init__.py
DuizhengXiayaoZhinvxingFenleixue/js/epub.js
DuizhengXiayaoZhinvxingFenleixue/js/epub.min.js
DuizhengXiayaoZhinvxingFenleixue/js/epub.min.map
DuizhengXiayaoZhinvxingFenleixue/js/hooks.min.js
DuizhengXiayaoZhinvxingFenleixue/js/hooks.min.map
DuizhengXiayaoZhinvxingFenleixue/js/reader.js
DuizhengXiayaoZhinvxingFenleixue/js/reader.js.map
DuizhengXiayaoZhinvxingFenleixue/js/reader.min.js
DuizhengXiayaoZhinvxingFenleixue/js/reader.min.map
DuizhengXiayaoZhinvxingFenleixue/js/hooks/__init__.py
duizheng_xiayao_zhinvxing_fenleixue-2022.10.11.0.dist-info/METADATA
duizheng_xiayao_zhinvxing_fenleixue-2022.10.11.0.dist-info/WHEEL
duizheng_xiayao_zhinvxing_fenleixue-2022.10.11.0.dist-info/entry_points.txt
duizheng_xiayao_zhinvxing_fenleixue-2022.10.11.0.dist-info/top_level.txt
duizheng_xiayao_zhinvxing_fenleixue-2022.10.11.0.dist-info/RECORD
